unsplashx/__init__.py
unsplashx/unsplashx.py
unsplashx-0.1.3.dist-info/LICENSE
unsplashx-0.1.3.dist-info/WHEEL
unsplashx-0.1.3.dist-info/METADATA
unsplashx-0.1.3.dist-info/RECORD
