Metadata-Version: 2.1
Name: unsplashx
Version: 0.1.3
Summary: Unsplash eXplorer for Humans™
Home-page: https://pypi.org/project/unsplashx
License: BSD-3-Clause
Author: Yi Zhang
Author-email: yizhang.dev@gmail.com
Requires-Python: >=3.7,<4.0
Classifier: License :: OSI Approved :: BSD License
Classifier: Programming Language :: Python :: 3
Classifier: Programming Language :: Python :: 3.7
Classifier: Programming Language :: Python :: 3.8
Classifier: Programming Language :: Python :: 3.9
Classifier: Programming Language :: Python :: 3.10
Classifier: Programming Language :: Python :: 3.11
Project-URL: Documentation, https://github.com/imyizhang/unsplashx#documentation
Project-URL: Repository, https://github.com/imyizhang/unsplashx
